xamalk/__init__.py
xamalk-0.0.1.dist-info/LICENSE
xamalk-0.0.1.dist-info/METADATA
xamalk-0.0.1.dist-info/WHEEL
xamalk-0.0.1.dist-info/RECORD
